rasterio_code_analyzer/__init__.py
rasterio_code_analyzer/__main__.py
rasterio_code_analyzer-1.0.1.dist-info/DESCRIPTION.rst
rasterio_code_analyzer-1.0.1.dist-info/METADATA
rasterio_code_analyzer-1.0.1.dist-info/RECORD
rasterio_code_analyzer-1.0.1.dist-info/WHEEL
rasterio_code_analyzer-1.0.1.dist-info/metadata.json
rasterio_code_analyzer-1.0.1.dist-info/top_level.txt
