Metadata-Version: 2.0
Name: rasterio-code-analyzer
Version: 1.0.1
Summary: Rasterio code analyzer
Home-page: https://github.com/sgillies/rasterio-code-analyzer
Author: Sean Gillies
Author-email: sean.gillies@gmail.com
License: BSD
Platform: UNKNOWN
Provides-Extra: test
Provides-Extra: test
Requires-Dist: pytest; extra == 'test'
